{
    "version": "9.0.0",
    "description": "Comic and manga converter for ebook readers.",
    "homepage": "https://github.com/ciromattia/kcc",
    "license": "ISC",
    "depends": "extras/kindlegen",
    "architecture": {
        "64bit": {
            "url": "https://github.com/ciromattia/kcc/releases/download/v9.0.0/KCC_9.0.0.exe",
            "hash": "f3035c638ed140a4c150f77e36742b69db9c687ac0aa34577e9bc45638a356a0",
            "shortcuts": [
                [
                    "KCC.exe",
                    "Kindle Comic Converter"
                ]
            ]
        }
    },
    "innosetup": true,
    "checkver": "github",
    "autoupdate": {
        "architecture": {
            "64bit": {
                "url": "https://github.com/ciromattia/kcc/releases/download/v$version/KCC_$version.exe"
            }
        }
    }
}
